aiotraq/__init__.py
aiotraq/api/__init__.py
aiotraq/api/activity/__init__.py
aiotraq/api/activity/get_activity_timeline.py
aiotraq/api/activity/get_online_users.py
aiotraq/api/authentication/__init__.py
aiotraq/api/authentication/get_my_external_accounts.py
aiotraq/api/authentication/get_my_sessions.py
aiotraq/api/authentication/link_external_account.py
aiotraq/api/authentication/login.py
aiotraq/api/authentication/logout.py
aiotraq/api/authentication/revoke_my_session.py
aiotraq/api/authentication/unlink_external_account.py
aiotraq/api/bot/__init__.py
aiotraq/api/bot/activate_bot.py
aiotraq/api/bot/change_bot_icon.py
aiotraq/api/bot/connect_bot_ws.py
aiotraq/api/bot/create_bot.py
aiotraq/api/bot/delete_bot.py
aiotraq/api/bot/edit_bot.py
aiotraq/api/bot/get_bot.py
aiotraq/api/bot/get_bot_icon.py
aiotraq/api/bot/get_bot_logs.py
aiotraq/api/bot/get_bots.py
aiotraq/api/bot/get_channel_bots.py
aiotraq/api/bot/inactivate_bot.py
aiotraq/api/bot/let_bot_join_channel.py
aiotraq/api/bot/let_bot_leave_channel.py
aiotraq/api/bot/reissue_bot.py
aiotraq/api/channel/__init__.py
aiotraq/api/channel/create_channel.py
aiotraq/api/channel/edit_channel.py
aiotraq/api/channel/edit_channel_subscribers.py
aiotraq/api/channel/edit_channel_topic.py
aiotraq/api/channel/get_channel.py
aiotraq/api/channel/get_channel_events.py
aiotraq/api/channel/get_channel_pins.py
aiotraq/api/channel/get_channel_stats.py
aiotraq/api/channel/get_channel_subscribers.py
aiotraq/api/channel/get_channel_topic.py
aiotraq/api/channel/get_channel_viewers.py
aiotraq/api/channel/get_channels.py
aiotraq/api/channel/get_messages.py
aiotraq/api/channel/set_channel_subscribers.py
aiotraq/api/clip/__init__.py
aiotraq/api/clip/clip_message.py
aiotraq/api/clip/create_clip_folder.py
aiotraq/api/clip/delete_clip_folder.py
aiotraq/api/clip/edit_clip_folder.py
aiotraq/api/clip/get_clip_folder.py
aiotraq/api/clip/get_clip_folders.py
aiotraq/api/clip/get_clips.py
aiotraq/api/clip/unclip_message.py
aiotraq/api/file/__init__.py
aiotraq-0.2.5.dist-info/METADATA
aiotraq-0.2.5.dist-info/WHEEL
aiotraq-0.2.5.dist-info/RECORD
