Metadata-Version: 2.1
Name: aiotraq
Version: 0.2.5
Summary: Async ready traQ API Client
Home-page: https://github.com/toshi-pono/aiotraq
License: MIT
Keywords: traQ,API,async,httpx
Author: toshi00
Requires-Python: >=3.8,<4.0
Classifier: License :: OSI Approved :: MIT License
Classifier: Programming Language :: Python :: 3
Classifier: Programming Language :: Python :: 3.8
Classifier: Programming Language :: Python :: 3.9
Classifier: Programming Language :: Python :: 3.10
Classifier: Programming Language :: Python :: 3.11
Classifier: Programming Language :: Python :: 3.12
Requires-Dist: attrs (>=21.3.0)
Requires-Dist: httpx (>=0.20.0,<0.28.0)
Requires-Dist: python-dateutil (>=2.8.0,<3.0.0)
Project-URL: Repository, https://github.com/toshi-pono/aiotraq
Project-URL: Source Code, https://github.com/toshi-pono/aiotraq/tree/main/libs/aiotraq
